setup.py
loveallufev_crawler.egg-info/PKG-INFO
loveallufev_crawler.egg-info/SOURCES.txt
loveallufev_crawler.egg-info/dependency_links.txt
loveallufev_crawler.egg-info/not-zip-safe
loveallufev_crawler.egg-info/requires.txt
loveallufev_crawler.egg-info/top_level.txt
request_core/__init__.py
request_core/authenticate.py
request_core/request.py