Metadata-Version: 1.0
Name: loveallufev-crawler
Version: 0.1
Summary: The crawler module
Home-page: https://github.com/loveallufev/crawler
Author: Duc Trung NGUYEN
Author-email: ductrungkhtn@gmail.com
License: MIT
Platform: UNKNOWN
